pypolarity/__init__.py
pypolarity/main.py
pypolarity/sentiment.py
pypolarity/sentimentV2.py
pypolarity/sentimentV3.py
pypolarity/sentimentV4.py
pypolarity/test.py
pypolarity/sentiment/negative_adjectives.txt
pypolarity/sentiment/negative_new.txt
pypolarity/sentiment/negative_verbs.txt
pypolarity/sentiment/positive_new.txt
pypolarity-0.0.5.dist-info/LICENSE.txt
pypolarity-0.0.5.dist-info/METADATA
pypolarity-0.0.5.dist-info/WHEEL
pypolarity-0.0.5.dist-info/top_level.txt
pypolarity-0.0.5.dist-info/RECORD
