Metadata-Version: 2.1
Name: pypolarity
Version: 0.0.5
Summary: analyze news article as positive or negative
Home-page: UNKNOWN
Author: sumeth
Author-email: author@example.com
License: MIT
Platform: UNKNOWN
Requires-Python: >=3.6
Requires-Dist: numpy
Requires-Dist: cut-sent-thai (>=0.0.9)
Requires-Dist: pythainlp (>=2.2.0)
Requires-Dist: ujson
